{"trial_id": "0", "hyperparameters": {"space": [{"class_name": "Choice", "config": {"name": "optimizer", "default": "adam", "conditions": [], "values": ["adam", "sgd", "rmsprop", "adadelta"], "ordered": false}}], "values": {"optimizer": "rmsprop"}}, "metrics": {"metrics": {"accuracy": {"direction": "max", "observations": [{"value": [0.7361563444137573], "step": 4}]}, "loss": {"direction": "min", "observations": [{"value": [0.5698754191398621], "step": 4}]}, "val_accuracy": {"direction": "max", "observations": [{"value": [0.7142857313156128], "step": 4}]}, "val_loss": {"direction": "min", "observations": [{"value": [0.573948860168457], "step": 4}]}}}, "score": 0.7142857313156128, "best_step": 4, "status": "COMPLETED", "message": null}